a42/__init__.py
a42/common.py
a42/data.py
a42/frame.py
a42/label.py
a42/sensors.py
a42_proto-0.4.1.dist-info/METADATA
a42_proto-0.4.1.dist-info/WHEEL
a42_proto-0.4.1.dist-info/top_level.txt
a42_proto-0.4.1.dist-info/RECORD
