Metadata-Version: 2.4
Name: a42_proto
Version: 0.4.1
Summary: Protobuf Python bindings for A42 sensor data
Author-email: Alexander Baumann <alexander.baumann@hs-esslingen.de>
License: MIT
Project-URL: Homepage, https://github.com/HSE-VSV/DataReaderA42
Requires-Python: >=3.6
Requires-Dist: protobuf
Requires-Dist: numpy
Requires-Dist: betterproto
Provides-Extra: dev
